src/branch_unit.sv
/*
    File name: branch_unit.sv
    Description: This file contains the module for the branch unit.
    Author: Marko Gjorgjievski
    Date: 15.01.2025
*/

import pkg_config::*;

`define BRANCH_BEQ      3'b000 // Branch Equal
`define BRANCH_BNE      3'b001 // Branch Not Equal
`define BRANCH_BLT      3'b100 // Branch Less Than
`define BRANCH_BGE      3'b101 // Branch Greater Than Or Equal
`define BRANCH_BLTU     3'b110 // Branch Less Than Unsigned
`define BRANCH_BGEU     3'b111 // Branch Greater Than Or Equal Unsigned
`define BRANCH_JAL_JALR 3'b010 // Jump in case of JAL or JALR instruction

module branch_unit (
    input wire branch_i,
    input wire [2:0] branch_op_i,
    input wire [DATA_WIDTH - 1:0] a_i,
    input wire [DATA_WIDTH - 1:0] b_i,
    output logic take_o
);

    always_comb begin
        take_o = 0;
        if (branch_i) begin
            case (branch_op_i)
                `BRANCH_BEQ:    take_o = (a_i == b_i);
                `BRANCH_BNE:    take_o = (a_i != b_i);
                `BRANCH_BLT:    take_o = ($signed(a_i) < $signed(b_i));
                `BRANCH_BGE:    take_o = ($signed(a_i) >= $signed(b_i));
                `BRANCH_BLTU:   take_o = (a_i < b_i);
                `BRANCH_BGEU:   take_o = (a_i >= b_i);
                `BRANCH_JAL_JALR: take_o = 1;
                default:        take_o = 0;
            endcase
        end
    end

endmodule

tb/branch_unit_tb.sv
/*
    File name: branch_unit.sv
    Description: This file contains the testbench for the branch unit.
    Author: Marko Gjorgjievski
    Date: 15.01.2025
*/

import pkg_config::*;

`default_nettype none
`timescale 1ns/1ns

module branch_unit_tb;

    logic clk;
    logic branch_i = 1'b0;
    logic [2:0] branch_op_i = 3'b000;
    logic [DATA_WIDTH-1:0] a_i = 32'h00000000;
    logic [DATA_WIDTH-1:0] b_i = 32'h00000000;
    logic take_o;

    // Device Under Test (DUT)
    branch_unit dut (
        .branch_i(branch_i),
        .branch_op_i(branch_op_i),
        .a_i(a_i),
        .b_i(b_i),
        .take_o(take_o)
    );

    // Clock reset.
    initial clk = 1'b0;
    // Clock generation.
    always #18.52 clk = ~clk;

    initial begin
        // Test 1: BEQ (Branch Equal)
        a_i = 32'h00000000;
        b_i = 32'h00000000;
        branch_i = 1'b1;
        branch_op_i = BRANCH_BEQ;
        #37.04;
        assert(take_o == 1'b1) else $fatal(1,"Assertion failed: take_o != 1'b1 at time %0t", $time);

        // Test 2: BNE (Branch Not Equal)
        branch_op_i = BRANCH_BNE;
        #37.04;
        assert(take_o == 1'b0) else $fatal(1,"Assertion failed: take_o != 1'b0 at time %0t", $time);

        // Test 3: BNE with unequal values
        a_i = 32'h00000000;
        b_i = 32'h00000001;
        #37.04;
        assert(take_o == 1'b1) else $fatal(1,"Assertion failed: take_o != 1'b1 at time %0t", $time);

        // Test 4: BLT (Branch Less Than)
        a_i = 32'h11111111; // -1
        b_i = 32'h11111110; // -2
        branch_op_i = BRANCH_BLT;
        #37.04;
        assert(take_o == 1'b0) else $fatal(1,"Assertion failed: take_o != 1'b0 at time %0t", $time);

        // Test 5: BGE (Branch Greater Than or Equal)
        branch_op_i = BRANCH_BGE;
        #37.04;
        assert(take_o == 1'b1) else $fatal(1,"Assertion failed: take_o != 1'b1 at time %0t", $time);

        // Test 6: BLTU (Branch Less Than Unsigned)
        branch_op_i = BRANCH_BLTU;
        #37.04;
        assert(take_o == 1'b0) else $fatal(1,"Assertion failed: take_o != 1'b0 at time %0t", $time);

        // Test 7: BGEU (Branch Greater Than or Equal Unsigned)
        branch_op_i = BRANCH_BGEU;
        #37.04;
        assert(take_o == 1'b1) else $fatal(1,"Assertion failed: take_o != 1'b1 at time %0t", $time);

        // Test 8: JAL/JALR (Always branch)
        branch_op_i = BRANCH_JAL_JALR;
        #37.04;
        assert(take_o == 1'b1) else $fatal(1,"Assertion failed: take_o != 1'b1 at time %0t", $time);

        // Test 9: JAL/JALR with no branch
        branch_i = 1'b0;
        #37.04;
        assert(take_o == 1'b0) else $fatal(1,"Assertion failed: take_o != 1'b0 at time %0t", $time);

        $finish;
    end

    // Display outputs during simulation
    always @(posedge clk) begin
        $display("time %2t, branch_i = %b, branch_op_i = %3b, a_i = %8h, b_i = %8h, take_o = %b", 
                 $time, branch_i, branch_op_i, a_i, b_i, take_o);
    end 

    // VCD dump for waveform generation
    initial begin
        $dumpfile("../../../../../../sim/branch_unit.vcd");
        $dumpvars;
    end

endmodule

sim/branch_unit.vcd
$date
   Sat Mar 15 11:31:50 2025
$end

$version
  2024.2.1
  $dumpfile ("../../../../../../sim/branch_unit.vcd") 
$end

$timescale
  1ps
$end

$scope module branch_unit_tb $end
$var reg 1 ! clk $end
$var reg 1 " branch_i $end
$var reg 3 # branch_op_i [2:0] $end
$var reg 32 $ a_i [31:0] $end
$var reg 32 % b_i [31:0] $end
$var reg 1 & take_o $end
$scope module dut $end
$var wire 1 ' branch_i $end
$var wire 3 ( branch_op_i [2:0] $end
$var wire 32 ) a_i [31:0] $end
$var wire 32 * b_i [31:0] $end
$var reg 1 & take_o $end
$upscope $end
$upscope $end
$enddefinitions $end

#0
$dumpvars
0!
1"
b0 #
b0 $
b0 %
1&
1'
b0 (
b0 )
b0 *
$end

#19000
1!

#37000
b1 #
0&
b1 (

#38000
0!

#57000
1!

#74000
b1 %
1&
b1 *

#76000
0!

#95000
1!

#111000
b100 #
b10001000100010001000100010001 $
b10001000100010001000100010000 %
0&
b100 (
b10001000100010001000100010001 )
b10001000100010001000100010000 *

#114000
0!

#133000
1!

#148000
b101 #
1&
b101 (

#152000
0!

#171000
1!

#185000
b110 #
0&
b110 (

#190000
0!

#209000
1!

#222000
b111 #
1&
b111 (

#228000
0!

#247000
1!

#259000
b10 #
1&
b10 (

#266000
0!

#285000
1!

#296000
0"
0&
0'

