src/sign_extension_unit.sv
/*
    File name: sign_extension_unit.sv
    Description: Sign extension units derive the immediate values from
                an instruction's fields depending on which type of 
                instruction is used.
    Author: Marko Gjorgjievski
    Date created: 15.03.2025
    Date modified: 14.04.2025
*/

import pkg_config::*;

module sign_extension (
    input wire [INST_WIDTH - 1:0] inst_i,                // Original 32-bit instruction
    input wire [OPCODE - 1:0] opcode_i,                   // Opcode for instruction
    output logic [DATA_WIDTH - 1:0] immediate_extended_o   // Extended 32-bit immediate value    
);

    // Sign-extend the immediate value based on the opcode
    always @* begin
        unique case (opcode_i)

            OP_ALUI, OP_LOAD, OP_JALR:  // ALU Immediate, Load, and JALR
                immediate_extended_o = $signed(inst_i[31:20]); // Sign-extend for immediate

            OP_STORE:  // Store Instructions (SB, SH, SW)
                immediate_extended_o = $signed({inst_i[31:25], inst_i[11:7]});

            OP_LUI, OP_AUIPC:  // LUI (Load Upper Immediate), AUIPC (Add Upper Immediate to PC)
                immediate_extended_o = {inst_i[31:12], 12'h000}; // Upper 20 bits are used, lower 12 bits are zero

            OP_JAL:  // JAL (Jump and Link)
                immediate_extended_o = $signed({inst_i[31], inst_i[19:12], inst_i[20], inst_i[30:21], 1'b0}); // Jump address calculation

            OP_BRANCH:  // Branch Instructions (BEQ, BNE, BLT, etc.)
                immediate_extended_o = $signed({inst_i[31], inst_i[7], inst_i[30:25], inst_i[11:8], 1'b0}); // Branch target address calculation
                                                
            default:
                immediate_extended_o = 32'hFFFF_FFFF; // Default to all ones for invalid opcodes
        endcase
    end

endmodule

tb/sign_extension_unit_tb.sv
/*
    File name: sign_extension_unit_tb.sv
    Description: This file contains the testbench 
                for the sign extension unit.
    Author: Marko Gjorgjievski
    Date: 15.03.2025
*/

import pkg_config::*;

`default_nettype none
`timescale 1ns/1ns

module sign_extension_tb;

    logic clk;
    logic [INST_WIDTH - 1:0] inst = 32'h00000000;
    logic [OPCODE - 1:0] opcode = `OP_ALUI;
    wire [INST_WIDTH - 1:0] immediate_extended;

    sign_extension dut (
        .inst_i(inst),
        .opcode_i(opcode),    
        .immediate_extended_o(immediate_extended)
    );

    // Clock reset.
    initial clk = 1'b0;

    always #18.52 clk = ~clk;
  
    initial begin
        inst = 32'h80000000;
        opcode = `OP_ALUI;
        #37.04;
        assert(immediate_extended == 32'hffff_f800) else $fatal("Assertion failed: immediate != ffff_f800 at time %0t", $time);

        inst = 32'h10100000;
        opcode = `OP_LOAD;
        #37.04;
        assert(immediate_extended == 32'h0000_0101) else $fatal("Assertion failed: immediate != 0000_0101 at time %0t", $time);

        inst = 32'h80F80023;
        opcode = `OP_STORE;
        #37.04;
        assert(immediate_extended == 32'hffff_f800) else $fatal("Assertion failed: immediate != ffff_f800 at time %0t", $time);

        inst = 32'h00F80023;
        opcode = `OP_STORE;
        #37.04;
        assert(immediate_extended == 32'h0000_0000) else $fatal("Assertion failed: immediate != 0000_0000 at time %0t", $time);

        inst = 32'h000170b7;
        opcode = `OP_LUI;
        #37.04;
        assert(immediate_extended == 32'h0001_7000) else $fatal("Assertion failed: immediate != 0001_7000 at time %0t", $time);

        inst = 32'h000170b7;
        opcode = `OP_AUIPC;
        #37.04;        
        assert(immediate_extended == 32'h0001_7000) else $fatal("Assertion failed: immediate != 0001_7000 at time %0t", $time);        

        inst = 32'h0e80026f;
        opcode = `OP_JAL;
        #37.04;
        assert(immediate_extended == 32'h0000_00e8) else $fatal("Assertion failed: immediate != 0000_00e8 at time %0t", $time);
        
        inst = 32'hf19ff26f;
        opcode = `OP_JAL;
        #37.04;
        assert(immediate_extended == 32'hffff_ff18) else $fatal("Assertion failed: immediate != ffff_ff18 at time %0t", $time);

        inst = 32'h00c00167;
        opcode = `OP_JALR;
        #37.04;
        assert(immediate_extended == 32'h0000_000c) else $fatal("Assertion failed: immediate != 0000_000c at time %0t", $time);

        inst = 32'hfe4104e3;
        opcode = `OP_BRANCH;
        #37.04;
        assert(immediate_extended == 32'hffff_ffe8) else $fatal("Assertion failed: immediate != ffff_ffe8 at time %0t", $time);

        $finish;
    end

    always @(posedge clk) begin
        $display("time %2t, inst = %8h, opcode = %7b, inst = %8h", $time, inst, opcode, immediate_extended);
    end 
  
    initial begin
        $dumpfile("../../../../../../sim/sign_extension.vcd");
        $dumpvars;  
    end

endmodule

sim/sign_extension.vcd
$date
   Fri Apr 11 13:30:59 2025
$end

$version
  2024.2.1
  $dumpfile ("../../../../../../sim/sign_extension.vcd") 
$end

$timescale
  1ps
$end

$scope module sign_extension_tb $end
$var reg 1 ! clk $end
$var reg 32 " inst [31:0] $end
$var reg 7 # opcode [6:0] $end
$var wire 32 $ immediate_extended [31:0] $end
$scope module dut $end
$var wire 32 % inst_i [31:0] $end
$var wire 7 & opcode_i [6:0] $end
$var reg 32 ' immediate_extended_o [31:0] $end
$upscope $end
$upscope $end
$enddefinitions $end

#0
$dumpvars
0!
b10000000000000000000000000000000 "
b10011 #
b11111111111111111111100000000000 $
b10000000000000000000000000000000 %
b10011 &
b11111111111111111111100000000000 '
$end

#20000
1!

#40000
0!
b10000000100000000000000000000 "
b11 #
b100000001 $
b10000000100000000000000000000 %
b11 &
b100000001 '

#60000
1!

#80000
0!
b10000000111110000000000000100011 "
b100011 #
b11111111111111111111100000000000 $
b10000000111110000000000000100011 %
b100011 &
b11111111111111111111100000000000 '

#100000
1!

#120000
0!
b111110000000000000100011 "
b0 $
b111110000000000000100011 %
b0 '

#140000
1!

#160000
0!
b10111000010110111 "
b110111 #
b10111000000000000 $
b10111000010110111 %
b110111 &
b10111000000000000 '

#180000
1!

#200000
0!
b10111 #
b10111 &

#220000
1!

#240000
0!
b1110100000000000001001101111 "
b1101111 #
b11101000 $
b1110100000000000001001101111 %
b1101111 &
b11101000 '

#260000
1!

#280000
0!
b11110001100111111111001001101111 "
b11111111111111111111111100011000 $
b11110001100111111111001001101111 %
b11111111111111111111111100011000 '

#300000
1!

#320000
0!
b110000000000000101100111 "
b1100111 #
b1100 $
b110000000000000101100111 %
b1100111 &
b1100 '

#340000
1!

#360000
0!
b11111110010000010000010011100011 "
b1100011 #
b11111111111111111111111111101000 $
b11111110010000010000010011100011 %
b1100011 &
b11111111111111111111111111101000 '

#380000
1!

#400000
0!
b10100000000001010010011 "
b10011 #
b101 $
b10100000000001010010011 %
b10011 &
b101 '

