src/Archive-TAP/tap_bypass_reg.sv
/*
    File name: tap_bypass_reg.sv
    Description:
    Author: Marko Gjorgjievski
    Date created: 25.04.2025
*/

module tap_bypass_reg (
    input logic tck_i,
    input logic tdi_i,
    input logic bypassEna_i,
    output logic tdo_o
);

    always_ff @(posedge tck_i) begin
        if(bypassEna_i) begin
            tdo_o <= tdi_i; //Only simple shifting
        end
    end

endmodule

tb/Archive-TAP/tap_bypass_reg_tb.sv
/*
    File name: tap_bypass_reg.sv
    Description: Testbench for the bypass register.
    Author: Marko Gjorgjievski
    Date created: 25.04.2025
*/

import tap_pkg::*;

`default_nettype none
`timescale 1ns/10ps // --> 18.52 clock edges.

module tap_bypass_reg_tb;

    // Testbench signals
    logic tck_i = 0;        // Clock
    logic tdi_i = 0;        // Test Data Input
    logic tdo_o = 0;        // Test Data Output
    logic bypassEna_i = 0;  // Enable bypass register
    logic [7:0] testData_s = 0;     // Test data pattern
    logic [7:0] testResult_s = 0;   // Result register filled.

    // Instantiate the DUT (tap_bypass)
    tap_bypass_reg dut (
        .tck_i(tck_i),
        .tdi_i(tdi_i),
        .bypassEna_i(bypassEna_i),
        .tdo_o(tdo_o)
    );

    // Clock generation
    initial begin
        $display("Starting tap_bypass_reg Testbench...");
        bypassEna_i = 1;
        testData_s = 8'b10101011; // Example test pattern
        forever #18.52 tck_i = ~tck_i; // 18.52 ns clock period matching TANG NANO 9K
    end

    initial begin
        for (int i = 0; i < 8; i++) begin
            @(posedge tck_i)
            assert(tdo_o == tdi_i) else $fatal(1,"Assertion failed tdo_o == tdi_i at time %0t", $time);
            tdi_i = testData_s[i];
            #10ps; //Smallest possible time delay as to fill testResult vector correctly.
            testResult_s[i] = tdo_o; // --> runs at same simulation step...
        end
        
        assert(testData_s == testResult_s) else $fatal(1,"Assertion failed testData_s != testResult_s at time %0t", $time);
        
        #10;
        $display("All bits passed successfully!");
        $finish;
    end

    always @(posedge tck_i) begin 
        $display("time %2t, tdi_i = %b, tdo_o = %b, testResult_s = %b", 
        $time, tdi_i, tdo_o, testResult_s); // tdo_o will be delayed 1 clk cycle.
    end 

    initial begin
        $dumpfile("../../../../../../sim/tap_bypass_reg.vcd");
        $dumpvars;
    end

endmodule

sim/tap_bypass_reg.vcd
$date
   Sat Apr 26 04:20:21 2025
$end

$version
  2024.2.1
  $dumpfile ("../../../../../../sim/tap_bypass_reg.vcd") 
$end

$timescale
  1ps
$end

$scope module tap_bypass_reg_tb $end
$var reg 1 ! tck_i $end
$var reg 1 " tdi_i $end
$var reg 1 # tdo_o $end
$var reg 1 $ bypassEna_i $end
$var reg 8 % testData_s [7:0] $end
$var reg 8 & testResult_s [7:0] $end
$scope module dut $end
$var wire 1 ' tck_i $end
$var wire 1 ( tdi_i $end
$var wire 1 ) bypassEna_i $end
$var reg 1 # tdo_o $end
$upscope $end
$scope begin Block40_3 $end
$var reg 32 * i [31:0] $end
$upscope $end
$upscope $end
$enddefinitions $end

#0
$dumpvars
0!
0"
0#
1$
b10101011 %
b0 &
0'
0(
1)
b0 *
$end

#18520
1!
1"
1#
1'
1(

#18530
b1 &
b1 *

#37040
0!
0'

#55560
1!
1'

#55570
b11 &
b10 *

#74080
0!
0'

#92600
1!
0"
0#
1'
0(

#92610
b11 *

#111120
0!
0'

#129640
1!
1"
1#
1'
1(

#129650
b1011 &
b100 *

#148160
0!
0'

#166680
1!
0"
0#
1'
0(

#166690
b101 *

#185200
0!
0'

#203720
1!
1"
1#
1'
1(

#203730
b101011 &
b110 *

#222240
0!
0'

#240760
1!
0"
0#
1'
0(

#240770
b111 *

#259280
0!
0'

#277800
1!
1"
1#
1'
1(
